README.rst
setup.py
sefara/__init__.py
sefara/environment.py
sefara/exporting.py
sefara/hooks.py
sefara/loading.py
sefara/resource.py
sefara/resource_collection.py
sefara/util.py
sefara.egg-info/PKG-INFO
sefara.egg-info/SOURCES.txt
sefara.egg-info/dependency_links.txt
sefara.egg-info/entry_points.txt
sefara.egg-info/requires.txt
sefara.egg-info/top_level.txt
sefara/commands/__init__.py
sefara/commands/check.py
sefara/commands/dump.py
sefara/commands/env.py
sefara/commands/select.py
sefara/commands/util.py
test/test_commands.py
test/test_resource_collection.py