Metadata-Version: 1.1
Name: sefara
Version: 0.2.1
Summary: Practical dataset management
Home-page: https://github.com/timodonnell/sefara
Author: Tim O'Donnell
Author-email: timodonnell@gmail.com
License: Apache License
Download-URL: https://github.com/timodonnell/sefara/tarball/0.2.1
Platform: UNKNOWN
Classifier: Development Status :: 1 - Planning
Classifier: Intended Audience :: Developers
Classifier: License :: OSI Approved :: MIT License
Classifier: Programming Language :: Python :: 2
Classifier: Programming Language :: Python :: 2.7
Classifier: Programming Language :: Python :: 3
Classifier: Programming Language :: Python :: 3.4
